odoo/addons/rma_reason/README.rst
odoo/addons/rma_reason/__init__.py
odoo/addons/rma_reason/__manifest__.py
odoo/addons/rma_reason/demo/rma_reason.xml
odoo/addons/rma_reason/i18n/it.po
odoo/addons/rma_reason/i18n/rma_reason.pot
odoo/addons/rma_reason/models/__init__.py
odoo/addons/rma_reason/models/res_company.py
odoo/addons/rma_reason/models/res_config_settings.py
odoo/addons/rma_reason/models/rma.py
odoo/addons/rma_reason/models/rma_reason.py
odoo/addons/rma_reason/readme/CONFIGURE.md
odoo/addons/rma_reason/readme/CONTRIBUTORS.md
odoo/addons/rma_reason/readme/DESCRIPTION.md
odoo/addons/rma_reason/readme/USAGE.md
odoo/addons/rma_reason/security/rma_reason.xml
odoo/addons/rma_reason/static/description/icon.png
odoo/addons/rma_reason/static/description/index.html
odoo/addons/rma_reason/tests/__init__.py
odoo/addons/rma_reason/tests/test_rma.py
odoo/addons/rma_reason/views/res_config_settings.xml
odoo/addons/rma_reason/views/rma.xml
odoo/addons/rma_reason/views/rma_portal_templates.xml
odoo/addons/rma_reason/views/rma_reason.xml
odoo/addons/rma_reason/wizards/__init__.py
odoo/addons/rma_reason/wizards/stock_return_picking.py
odoo/addons/rma_reason/wizards/stock_return_picking.xml
odoo/addons/rma_reason/wizards/stock_return_picking_line.py
odoo_addon_rma_reason-18.0.1.0.0.2.dist-info/METADATA
odoo_addon_rma_reason-18.0.1.0.0.2.dist-info/WHEEL
odoo_addon_rma_reason-18.0.1.0.0.2.dist-info/top_level.txt
odoo_addon_rma_reason-18.0.1.0.0.2.dist-info/RECORD
