Metadata-Version: 2.1
Name: odoo-addon-rma_reason
Version: 18.0.1.0.0.2
Requires-Python: >=3.10
Requires-Dist: odoo-addon-rma==18.0.*
Requires-Dist: odoo==18.0.*
Summary: Rma Reason
Home-page: https://github.com/OCA/rma
License: AGPL-3
Author: Raumschmiede GmbH,BCIM,ACSONE SA/NV,Odoo Community Association (OCA)
Author-email: support@odoo-community.org
Classifier: Programming Language :: Python
Classifier: Framework :: Odoo
Classifier: Framework :: Odoo :: 18.0
Classifier: License :: OSI Approved :: GNU Affero General Public License v3
